opendvp/__init__.py
opendvp/experimental/plot_MLM_heatmap.py
opendvp/experimental/plot_ORA_heatmap.py
opendvp/experimental/plot_ORA_source_variables.py
opendvp/imaging/__init__.py
opendvp/imaging/mask_to_polygons.py
opendvp/io/DIANN_to_adata.py
opendvp/io/__init__.py
opendvp/io/adata_to_qupath.py
opendvp/io/adata_to_voronoi.py
opendvp/io/export_adata.py
opendvp/io/export_figure.py
opendvp/io/import_perseus.py
opendvp/io/import_thresholds.py
opendvp/io/quant_to_adata.py
opendvp/io/segmask_to_qupath.py
opendvp/metrics/__init__.py
opendvp/metrics/coefficient_of_variation.py
opendvp/metrics/nan_difference.py
opendvp/plotting/__init__.py
opendvp/plotting/abundance_histograms.py
opendvp/plotting/coefficient_of_variation.py
opendvp/plotting/correlation_heatmap.py
opendvp/plotting/density.py
opendvp/plotting/dual_axis_boxplots.py
opendvp/plotting/feature_comparison_boxplot.py
opendvp/plotting/imputation_qc.py
opendvp/plotting/pca_loadings.py
opendvp/plotting/plot_graph_network.py
opendvp/plotting/rankplot.py
opendvp/plotting/stacked_barplot.py
opendvp/plotting/upset.py
opendvp/plotting/volcano.py
opendvp/pp/__init__.py
opendvp/pp/impute_marker_with_annotation.py
opendvp/pp/scimap_rescale.py
opendvp/tl/__init__.py
opendvp/tl/filter_by_abs_value.py
opendvp/tl/filter_by_annotation.py
opendvp/tl/filter_by_ratio.py
opendvp/tl/filter_features_byNaNs.py
opendvp/tl/impute_gaussian.py
opendvp/tl/scimap_phenotype.py
opendvp/tl/scimap_spatial_cluster.py
opendvp/tl/scimap_spatial_lda.py
opendvp/tl/spatial_autocorrelation.py
opendvp/tl/spatial_hyperparameter_search.py
opendvp/tl/stats_anova.py
opendvp/tl/stats_average_samples.py
opendvp/tl/stats_bootstrap.py
opendvp/tl/stats_ttest.py
opendvp/utils/__init__.py
opendvp/utils/logger.py
opendvp/utils/parse_color_for_qupath.py
opendvp/utils/utils.py
opendvp-0.7.3.dist-info/WHEEL
opendvp-0.7.3.dist-info/METADATA
opendvp-0.7.3.dist-info/RECORD
