Metadata-Version: 2.3
Name: opendvp
Version: 0.7.3
Summary: open-sourced Deep Visual Proteomics toolkit
Author: Jose Nimo
Author-email: Jose Nimo <jose.nimo@mdc-berlin.de>
License:                     GNU GENERAL PUBLIC LICENSE
Requires-Dist: numpy>=2.0.0
Requires-Dist: spatialdata>=0.4.0
Requires-Dist: napari-spatialdata==0.5.5
Requires-Dist: spatialdata-plot~=0.2.9
Requires-Dist: ipykernel~=6.25
Requires-Dist: scanpy>=1.11,<1.14
Requires-Dist: loguru~=0.7.3
Requires-Dist: scipy~=1.13
Requires-Dist: statsmodels>=0.14.5
Requires-Dist: adjusttext
Requires-Dist: pingouin>=0.5.5,<0.6
Requires-Dist: esda>=2.7,<2.8
Requires-Dist: upsetplot
Requires-Dist: perseuspy>=0.3.9,<0.4
Requires-Dist: gensim~=4.4.0
Requires-Dist: pyqt6
Requires-Dist: tifffile>=2025.9.30
Requires-Dist: scikit-image>=0.25.2
Requires-Dist: scikit-learn>=1.7.2
Requires-Dist: xarray>=2024.11.0
Requires-Dist: pyogrio>=0.11.1
Maintainer: Jose Nimo
Maintainer-email: Jose Nimo <jose.nimo@mdc-berlin.de>
Requires-Python: >=3.11, <3.14
Project-URL: Documentation, https://coscialab.github.io/openDVP/
Project-URL: Homepage, https://github.com/CosciaLab/openDVP
Project-URL: Source, https://github.com/CosciaLab/openDVP
